pysamiterators/__init__.py
pysamiterators/iterators/__init__.py
pysamiterators/iterators/iterators.py
pysamiterators-1.9.dist-info/LICENSE
pysamiterators-1.9.dist-info/METADATA
pysamiterators-1.9.dist-info/WHEEL
pysamiterators-1.9.dist-info/top_level.txt
pysamiterators-1.9.dist-info/RECORD
