Metadata-Version: 2.1
Name: pysamiterators
Version: 1.9
Summary: Pysam related iterators
Home-page: https://github.com/BuysDB/pysamiterators
Author: Buys de Barbanson
Author-email: code@buysdb.nl
License: MIT
Download-URL: https://github.com/BuysDB/pysamiterators/archive/v1.08.tar.gz
Keywords: mate-pair,pysam,iteration
Platform: UNKNOWN
Classifier: Development Status :: 4 - Beta
Classifier: Programming Language :: Python :: 3.4
Classifier: Programming Language :: Python :: 3.5
Classifier: Programming Language :: Python :: 3.6
Classifier: License :: OSI Approved :: MIT License
Requires-Dist: pysam
Requires-Dist: numpy
